bixomix/__init__.py
bixomix/dates.py
bixomix/py.typed
bixomix/states.py
bixomix-0.1.2.dist-info/LICENSE
bixomix-0.1.2.dist-info/METADATA
bixomix-0.1.2.dist-info/WHEEL
bixomix-0.1.2.dist-info/RECORD
