Metadata-Version: 2.1
Name: bixomix
Version: 0.1.2
Summary: Collection of SQLAlchemy mixins
Home-page: https://github.com/Bixoto/bixomix
License: MIT
Author: Baptiste Fontaine
Author-email: baptiste@bixoto.com
Requires-Python: >=3.9,<4.0
Classifier: Development Status :: 5 - Production/Stable
Classifier: License :: OSI Approved :: MIT License
Classifier: Programming Language :: Python :: 3
Classifier: Programming Language :: Python :: 3.9
Classifier: Programming Language :: Python :: 3.10
Classifier: Programming Language :: Python :: 3.11
Classifier: Programming Language :: Python :: 3.12
Requires-Dist: sqlalchemy (>=2.0,<3.0)
